{"cameraMode":{"drawMode":0,"name":"Shaded","section":"Shading Mode"},"sceneLighting":false,"audioPlay":false,"sceneViewState":{"showFog":true,"showMaterialUpdate":false,"showSkybox":false,"showFlares":true,"showImageEffects":true,"showParticleSystems":true},"in2DMode":false,"pivot":{"x":20.853591918945314,"y":1.218398094177246,"z":48.377784729003909},"rotation":{"x":0.3451041281223297,"y":0.029087666422128679,"z":-0.01069871336221695,"w":0.9382500052452087},"size":87.83751678466797,"orthographic":false}